setup.cfg
setup.py
libpaas/__init__.py
libpaas/settings.py
libpaas/camp/__init__.py
libpaas/camp/models.py
libpaas/camp/pdpparser.py
libpaas/camp/planparser.py
libpaas/drivers/__init__.py
libpaas/drivers/base.py
libpaas/drivers/heroku.py
libpaas/drivers/manager.py
libpaas/drivers/openshift.py
libpaas/paascli/__init__.py
libpaas/paascli/appcmds.py
libpaas/paascli/config.py
libpaas/paascli/db.py
libpaas/paascli/paascli.py
paascli.egg-info/PKG-INFO
paascli.egg-info/SOURCES.txt
paascli.egg-info/dependency_links.txt
paascli.egg-info/entry_points.txt
paascli.egg-info/requires.txt
paascli.egg-info/top_level.txt