Metadata-Version: 1.1
Name: paascli
Version: 0.2
Summary: paascli is a CLI toolbelt to manage CAMP compliant apps across multiple PaaS providers
Home-page: https://github.com/hvishwanath/libpaas
Author: Harish Vishwanath
Author-email: harish.shastry@gmail.com
License: MIT
Download-URL: https://github.com/hvishwanath/libpaas/tarball/master
Keywords: testing,logging,example
Platform: UNIX
